cutseq/adapters.toml
cutseq/common.py
cutseq/run.py
cutseq-0.0.68.dist-info/METADATA
cutseq-0.0.68.dist-info/WHEEL
cutseq-0.0.68.dist-info/entry_points.txt
cutseq-0.0.68.dist-info/RECORD
