Metadata-Version: 2.4
Name: cutseq
Version: 0.0.68
Summary: Automatically cut adapter / barcode / UMI from NGS data
Project-URL: Repository, https://github.com/y9c/cutseq
Author-email: Ye Chang <yech1990@gmail.com>
License-Expression: MIT
Keywords: NGS,UMI,adapter,barcode,bioinformatics
Requires-Python: ~=3.9
Requires-Dist: cutadapt~=5.0
Requires-Dist: tomli<3,>=2.0.1; python_version < '3.11'
